[
  {
    "text": "Ich hatte keine Ahnung, dass meine Nahrungsergänzungsmittel aus Schafwolle hergestellt wurden – absolut schockierend.",
    "author": "Sarah M."
  },
  {
    "text": "Als ich die Wahrheit erfuhr, bin ich sofort auf pflanzliches Vitamin D3 umgestiegen.",
    "author": "Dr. James K."
  },
  {
    "text": "Der Prozess mit Lanolin hat mich angewidert – die Gewinnung aus Kiefernholz fühlt sich so viel sauberer an.",
    "author": "Michael R."
  },
  {
    "text": "Nachdem ich den Unterschied entdeckt hatte, konnte ich nie wieder zu aus Wolle gewonnenem D3 zurückkehren.",
    "author": "Emily T."
  },
  {
    "text": "Es ist eine Erleichterung zu wissen, dass mein Vitamin D3 nun aus einer rein pflanzlichen Quelle stammt.",
    "author": "David L."
  }
]